Metadata-Version: 1.0
Name: doctestpdbhacks
Version: 0.1
Summary: pdb doesn't play nice with doctests..  this is a quick hack to fix that.
Home-page: http://scryent.com
Author: Jordan Baker
Author-email: jbb AT scryent DOT com
License: UNKNOWN
Platform: UNKNOWN
